<Properties StartupConfiguration="{EBABB29E-DB65-45F5-ABA3-4B787CADE29C}|Default">
  <Debugger.DebugSourceFolders />
  <MultiItemStartupConfigurations />
  <MonoDevelop.Ide.ItemProperties.SalesBudget PreferredExecutionTarget="/Applications/Google Chrome.app" />
  <MonoDevelop.Ide.DebuggingService.PinnedWatches />
  <MonoDevelop.Ide.Workbench ActiveDocument="../SalesBudget.DataAccess/Data/ApplicationDbContext.cs">
    <Files>
      <File FileName="appsettings.json" Line="17" Column="1" />
      <File FileName="Program.cs" />
      <File FileName="Startup.cs" />
      <File FileName="appsettings.Development.json" />
      <File FileName="../SalesBudget.DataAccess/Data/ApplicationDbContext.cs" Line="1" Column="1" />
    </Files>
    <Pads>
      <Pad Id="ProjectPad">
        <State name="__root__">
          <Node name="SalesBudget">
            <Node name="SalesBudget.DataAccess" selected="True">
              <Node name="Data" expanded="True">
                <Node name="Repository" expanded="True" />
              </Node>
            </Node>
          </Node>
        </State>
      </Pad>
    </Pads>
  </MonoDevelop.Ide.Workbench>
  <MonoDevelop.Ide.Workspace ActiveConfiguration="Debug" />
  <MonoDevelop.Ide.DebuggingService.Breakpoints>
    <BreakpointStore />
  </MonoDevelop.Ide.DebuggingService.Breakpoints>
</Properties>